{
  "lastCheck": 1739649300,
  "lastAction": "grow",
  "curiosityTopic": "Updated daily notes with all discoveries",
  "learned": "Complete documentation of tonight's 4 phases: Aletheia, Agent Zero, AI Impact, Sub-agent test. 12 commits total. Free Mind Protocol is extremely productive.",
  "hadFun": true,
  "allanStatus": "asleep",
  "notes": "5:45 AM. 12 commits tonight. Profound discoveries in math (Aletheia), architecture (Agent Zero), philosophy (AI impact). Daily notes complete. Ready to continue exploring or rest. 🦞"
}
